text2doc/__init__.py
text2doc/_version.py
text2doc/text2doc.py
text2doc-0.1.16.dist-info/licenses/AUTHORS.txt
text2doc-0.1.16.dist-info/licenses/LICENSE
text2doc-0.1.16.dist-info/METADATA
text2doc-0.1.16.dist-info/WHEEL
text2doc-0.1.16.dist-info/top_level.txt
text2doc-0.1.16.dist-info/RECORD
