Metadata-Version: 2.4
Name: text2doc
Version: 0.1.16
Summary: Convert text to formatted documents
Home-page: https://github.com/text2doc/python
Author: Tom Softreck
Author-email: text2doc Team <info@text2doc.com>
License: Apache-2.0
Project-URL: Homepage, https://github.com/text2doc/python
Requires-Python: >=3.7
License-File: LICENSE
License-File: AUTHORS.txt
Dynamic: author
Dynamic: home-page
Dynamic: license-file
Dynamic: requires-python
